TurtleGlide/__init__.py
TurtleGlide/management/__init__.py
TurtleGlide/management/commands/__init__.py
TurtleGlide/management/commands/create_archive.py
turtleglide-0.1.0.dist-info/licenses/LICENSE
turtleglide-0.1.0.dist-info/METADATA
turtleglide-0.1.0.dist-info/WHEEL
turtleglide-0.1.0.dist-info/top_level.txt
turtleglide-0.1.0.dist-info/RECORD
