Metadata-Version: 2.4
Name: TurtleGlide
Version: 0.1.0
Summary: Comandos para crear archivos HTML, CSS y JS
Author-email: Alejandro <hjosealejandro21@gmail.com>
License-Expression: MPL-2.0
Project-URL: Github, https://github.com/jose-CR/TurtleGlide
Classifier: Environment :: Web Environment
Classifier: Framework :: Django :: 3.2
Classifier: Intended Audience :: Developers
Classifier: Operating System :: OS Independent
Classifier: Programming Language :: Python
License-File: LICENSE
Requires-Dist: django>=3.2
Dynamic: license-file
